setup.py
GB222distributions/Binomialdistribution.py
GB222distributions/Gaussiandistribution.py
GB222distributions/Generaldistribution.py
GB222distributions/__init__.py
GB222distributions.egg-info/PKG-INFO
GB222distributions.egg-info/SOURCES.txt
GB222distributions.egg-info/dependency_links.txt
GB222distributions.egg-info/not-zip-safe
GB222distributions.egg-info/top_level.txt