Metadata-Version: 1.0
Name: GB222distributions
Version: 1.2
Summary: Gaussian and Binomial distributions
Home-page: UNKNOWN
Author: bayode
Author-email: UNKNOWN
License: UNKNOWN
Platform: UNKNOWN
